hs/VERSION.txt
hs/__init__.py
hs/__pycache__/__init__.cpython-38.pyc
hs/api/__init__.py
hs/api/constant.py
hs/api/hs_common_api.py
hs/api/quote_api.py
hs/api/trading_api.py
hs/api/__pycache__/__init__.cpython-38.pyc
hs/api/__pycache__/constant.cpython-38.pyc
hs/api/__pycache__/quote_api.cpython-38.pyc
hs/api/__pycache__/trading_api.cpython-38.pyc
hs/bind/__init__.py
hs/bind/common_utils.py
hs/bind/device_bind.py
hs/bind/mobile_validator.py
hs/bind/network_request.py
hs/bind/network_utils.py
hs/bind/rsa_utils.py
hs/common/__init__.py
hs/common/aes_ecb.py
hs/common/common_utils.py
hs/common/network_utils.py
hs/common/protobuf_utils.py
hs/common/quote_socket_client.py
hs/common/request_msg_header.py
hs/common/request_msg_type_enum.py
hs/common/ring_buffer.py
hs/common/rsa_utils.py
hs/common/socket_client.py
hs/common/token_client.py
hs/common/trading_socket_client.py
hs/common/__pycache__/__init__.cpython-38.pyc
hs/common/__pycache__/aes_ecb.cpython-38.pyc
hs/common/__pycache__/common_utils.cpython-38.pyc
hs/common/__pycache__/network_utils.cpython-38.pyc
hs/common/__pycache__/protobuf_utils.cpython-38.pyc
hs/common/__pycache__/quote_socket_client.cpython-38.pyc
hs/common/__pycache__/request_msg_header.cpython-38.pyc
hs/common/__pycache__/request_msg_type_enum.cpython-38.pyc
hs/common/__pycache__/ring_buffer.cpython-38.pyc
hs/common/__pycache__/rsa_utils.cpython-38.pyc
hs/common/__pycache__/socket_client.cpython-38.pyc
hs/common/__pycache__/token_client.cpython-38.pyc
hs/common/__pycache__/trading_socket_client.cpython-38.pyc
hs/common/pb/__init__.py
hs/common/pb/protoc_tool.py
hs/common/pb/__pycache__/__init__.cpython-38.pyc
hs/common/pb/common/__init__.py
hs/common/pb/common/__pycache__/__init__.cpython-38.pyc
hs/common/pb/common/constant/NotifyMsgType.proto
hs/common/pb/common/constant/NotifyMsgType_pb2.py
hs/common/pb/common/constant/RequestMsgType.proto
hs/common/pb/common/constant/RequestMsgType_pb2.py
hs/common/pb/common/constant/ResponseMsgType.proto
py_sahm_openapi-1.0.9.dist-info/LICENSE
py_sahm_openapi-1.0.9.dist-info/METADATA
py_sahm_openapi-1.0.9.dist-info/WHEEL
py_sahm_openapi-1.0.9.dist-info/top_level.txt
py_sahm_openapi-1.0.9.dist-info/RECORD
